setup.py
samplechintan/__init__.py
samplechintan/add.py
samplechintan.egg-info/PKG-INFO
samplechintan.egg-info/SOURCES.txt
samplechintan.egg-info/dependency_links.txt
samplechintan.egg-info/top_level.txt