Metadata-Version: 1.0
Name: samplechintan
Version: 0.1.0
Summary: An example of python package.
Home-page: https://github.com/MarziyaFatema/demo
Author: Marziya
Author-email: shaikhmarzi05@gmail.com
License: UNKNOWN
Platform: UNKNOWN
